gino/__init__.py
gino/api.py
gino/crud.py
gino/declarative.py
gino/engine.py
gino/exceptions.py
gino/json_support.py
gino/loader.py
gino/schema.py
gino/strategies.py
gino/transaction.py
gino/dialects/__init__.py
gino/dialects/asyncpg.py
gino/dialects/base.py
gino/ext/__init__.py
gino/ext/aiohttp.py
gino/ext/quart.py
gino/ext/sanic.py
gino/ext/starlette.py
gino/ext/tornado.py
gino-0.8.7.dist-info/AUTHORS.rst
gino-0.8.7.dist-info/LICENSE
gino-0.8.7.dist-info/METADATA
gino-0.8.7.dist-info/WHEEL
gino-0.8.7.dist-info/entry_points.txt
gino-0.8.7.dist-info/top_level.txt
gino-0.8.7.dist-info/RECORD
