Metadata-Version: 2.1
Name: gino
Version: 0.8.7
Summary: GINO Is Not ORM - a Python asyncio ORM on SQLAlchemy core.
Home-page: https://github.com/fantix/gino
Author: Fantix King
Author-email: fantix.king@gmail.com
License: BSD license
Project-URL: Documentation, https://python-gino.readthedocs.io/
Project-URL: Funding, https://www.patreon.com/fantixking
Project-URL: Source, https://github.com/fantix/gino
Project-URL: Tracker, https://github.com/fantix/gino/issues
Keywords: orm asyncio sqlalchemy asyncpg python3 sanic aiohttp tornado
Platform: UNKNOWN
Classifier: Development Status :: 4 - Beta
Classifier: Intended Audience :: Developers
Classifier: License :: OSI Approved :: BSD License
Classifier: Natural Language :: English
Classifier: Programming Language :: Python :: 3
Classifier: Programming Language :: Python :: 3.5
Classifier: Programming Language :: Python :: 3.6
Classifier: Programming Language :: Python :: 3.7
Classifier: Programming Language :: Python :: 3.8
Requires-Python: >=3.5
Requires-Dist: asyncpg (~=0.18)
Requires-Dist: SQLAlchemy (~=1.2)
Requires-Dist: aiocontextvars (~=0.2)
